animapp/__init__.py
animapp/_version.py
animapp/animapp.py
animapp/process_csv.py
animapp/qrangeslider.py
animapp/set_thresholds.py
animapp/data_files/example_vid.mp4
animapp/data_files/settings.yaml
animapp-0.1.5.6.dist-info/LICENSE
animapp-0.1.5.6.dist-info/METADATA
animapp-0.1.5.6.dist-info/WHEEL
animapp-0.1.5.6.dist-info/entry_points.txt
animapp-0.1.5.6.dist-info/top_level.txt
animapp-0.1.5.6.dist-info/RECORD
